Workbook

Sheet 0_進め方
A1: 学習WBS（受講者版）— SD 見込生産（MTS）
A2: SAP S/4HANA 業務実践トレーニング / 記入式の進捗管理ワークブック（サイト版と同期）
A3: 本ワークブックの使い方 | B3: 本站は「予測で作り、在庫から納める」見込生産です。MTO（sapmto）と対比しながら進めると、「自由在庫 vs 受注在庫」「PIR vs 受注」「差異計算 vs 案件の進捗」の違いが腹に落ちます。
A4: 目安時間 | B4: 配置（C0〜C16）＋練習①〜⑤で「講義 1 日 ＋ 実機 1〜2 日」程度。
A5: 特に注意 | B5: PIR（MD61）と安全在庫の設定が需要を作ります。需要が無ければ MRP は何も作りません。まず MD04 で需要の正体（PIR か受注か）を読む習慣を付けてください。
A7: 凡例 | B7: ○ ＝ できた（完成基準を満たした）／△ ＝ 一部できた（要確認）／× ＝ できなかった。「2_進捗サマリ」にフェーズ別の完了率が自動計算されます。

Sheet 1_学習WBS
A1: 学習WBS — SD 見込生産（MTS）（上から順に実施）
A2: # | B2: フェーズ | C2: タスク | D2: 参照ページ | E2: 完成基準（ここを満たしたら ○） | F2: 目安(分) | G2: 実施日 | H2: 自己判定 | I2: メモ
A3: 1 | B3: A 総覧 | C3: 本站の環境と前提を説明できる | D3: index.html | E3: 得意先 1000 / 品目 / プラント / MRP エリアが利用可能であることを確認した | F3: 10
A4: 2 | B4: A 総覧 | C4: 見込生産の流れを白紙に書ける | D4: index.html | E4: 需要予測（PIR）→ MRP → 計画手配 → 指図 → 入庫（自由在庫）→ 受注 → 引当（ATP）→ 出荷 → 請求 を順に説明できる | F4: 10
A5: 3 | B5: A 総覧 | C5: 見込生産の 3 方式を区別できる | D5: index.html | E5: 品目レベル / 最終組立レベル / 組立レベル（戦略 10 / 30 / 40 系）の違いを説明できる | F5: 10
A6: 4 | B6: B 概念と設計 | C6: 自由在庫と受注在庫の違いを説明できる | D6: concept.html | E6: MARD（自由）と MSKA（特在 E）の違い、引当の起こり方を説明できる | F6: 10
A7: 5 | B7: B 概念と設計 | C7: PIR の役割を説明できる | D7: concept.html | E7: MD61 で作る需要予測が MRP の入力になり、受注が入ると消費される（消費モード）ことを説明できる | F7: 10
A8: 6 | B8: B 概念と設計 | C8: ネットチェンジを説明できる | D8: concept.html | E8: MRP 実行で計画手配の日付・数量がどう調整されるか、MD04 の行の見方を説明できる | F8: 10
A9: 7 | B9: B 概念と設計 | C9: 標準原価と差異の流れを説明できる | D9: concept.html | E9: 指図の投入 vs 出来高の差が差異になり、KKS1 / KO88 / CO88 で計算・決済されることを説明できる | F9: 10
A10: 8 | B10: B 概念と設計 | C10: 欠品・安全在庫の考え方を説明できる | D10: concept.html | E10: 安全在庫と ATP が欠品をどう防ぐか、不足時に何が起きるかを説明できる | F10: 10
A11: 9 | B11: C 配置（SPRO / マスタ） | C11: 前提与环境确认 | D11: config.html#c0 | E11: 確認（自システムでの確認方法） VA01 能进入输入画面并看到 販売エリア = 1000/10/00，即前提基本满足。 | F11: 15
A12: 10 | B12: C 配置（SPRO / マスタ） | C12: 部品品目（ZMTS-RM01 / ZMTS-RM02） | D12: config.html#c1 | E12: 確認（自システムでの確認方法） MMBE → 品目 ZMTS-RM01 / プラント 1000：非制限利用（自由在庫）1,000 PC。 | F12: 15
A13: 11 | B13: C 配置（SPRO / マスタ） | C13: 完成品品目 ZMTS-FG01（本教程最关键的一张主数据） | D13: config.html#c2 | E13: 確認（自システムでの確認方法） MM03 → ZMTS-FG01 → 追加ビュー選択 で MRP1/2/3/4 を順に開き、上表と一致するか。 | F13: 15
A14: 12 | B14: C 配置（SPRO / マスタ） | C14: BOM・作業区・作業手順（標準原価の入力でもある） | D14: config.html#c3 | E14: 確認（自システムでの確認方法） CS03 で明細 2 行、CA03 で工程 1 行。 | F14: 15
... A96: 94 | B96: J テスト | C96: 修了チェック（到達点）を通す | D96: quiz.html | E96: 修了チェックリストの全項目にチェックが付いた | F96: 30

Sheet 2_進捗サマリ
A1: 進捗サマリ（1_学習WBS の自己判定から自動集計）
A2: フェーズ | B2: タスク数 | C2: ○ | D2: △ | E2: × | F2: 完了率
A3: A 総覧 | B3: =COUNTIF('1_学習WBS'!$B$3:$B$96,$A3) | C3: =COUNTIFS('1_学習WBS'!$B$3:$B$96,$A3,'1_学習WBS'!$H$3:$H$96,"○") | D3: =COUNTIFS('1_学習WBS'!$B$3:$B$96,$A3,'1_学習WBS'!$H$3:$H$96,"△") | E3: =COUNTIFS('1_学習WBS'!$B$3:$B$96,$A3,'1_学習WBS'!$H$3:$H$96,"×") | F3: =IF(B3=0,"",ROUND(C3/B3*100,0)&" %")
A4: B 概念と設計 | B4: =COUNTIF('1_学習WBS'!$B$3:$B$96,$A4) | C4: =COUNTIFS('1_学習WBS'!$B$3:$B$96,$A4,'1_学習WBS'!$H$3:$H$96,"○") | D4: =COUNTIFS('1_学習WBS'!$B$3:$B$96,$A4,'1_学習WBS'!$H$3:$H$96,"△") | E4: =COUNTIFS('1_学習WBS'!$B$3:$B$96,$A4,'1_学習WBS'!$H$3:$H$96,"×") | F4: =IF(B4=0,"",ROUND(C4/B4*100,0)&" %")
A5: C 配置（SPRO / マスタ） | B5: =COUNTIF('1_学習WBS'!$B$3:$B$96,$A5) | C5: =COUNTIFS('1_学習WBS'!$B$3:$B$96,$A5,'1_学習WBS'!$H$3:$H$96,"○") | D5: =COUNTIFS('1_学習WBS'!$B$3:$B$96,$A5,'1_学習WBS'!$H$3:$H$96,"△") | E5: =COUNTIFS('1_学習WBS'!$B$3:$B$96,$A5,'1_学習WBS'!$H$3:$H$96,"×") | F5: =IF(B5=0,"",ROUND(C5/B5*100,0)&" %")
A6: D 練習① | B6: =COUNTIF('1_学習WBS'!$B$3:$B$96,$A6) | C6: =COUNTIFS('1_学習WBS'!$B$3:$B$96,$A6,'1_学習WBS'!$H$3:$H$96,"○") | D6: =COUNTIFS('1_学習WBS'!$B$3:$B$96,$A6,'1_学習WBS'!$H$3:$H$96,"△") | E6: =COUNTIFS('1_学習WBS'!$B$3:$B$96,$A6,'1_学習WBS'!$H$3:$H$96,"×") | F6: =IF(B6=0,"",ROUND(C6/B6*100,0)&" %")
A7: D 練習①（验收） | B7: =COUNTIF('1_学習WBS'!$B$3:$B$96,$A7) | C7: =COUNTIFS('1_学習WBS'!$B$3:$B$96,$A7,'1_学習WBS'!$H$3:$H$96,"○") | D7: =COUNTIFS('1_学習WBS'!$B$3:$B$96,$A7,'1_学習WBS'!$H$3:$H$96,"△") | E7: =COUNTIFS('1_学習WBS'!$B$3:$B$96,$A7,'1_学習WBS'!$H$3:$H$96,"×") | F7: =IF(B7=0,"",ROUND(C7/B7*100,0)&" %")
A8: E 練習② | B8: =COUNTIF('1_学習WBS'!$B$3:$B$96,$A8) | C8: =COUNTIFS('1_学習WBS'!$B$3:$B$96,$A8,'1_学習WBS'!$H$3:$H$96,"○") | D8: =COUNTIFS('1_学習WBS'!$B$3:$B$96,$A8,'1_学習WBS'!$H$3:$H$96,"△") | E8: =COUNTIFS('1_学習WBS'!$B$3:$B$96,$A8,'1_学習WBS'!$H$3:$H$96,"×") | F8: =IF(B8=0,"",ROUND(C8/B8*100,0)&" %")
A9: E 練習②（验收） | B9: =COUNTIF('1_学習WBS'!$B$3:$B$96,$A9) | C9: =COUNTIFS('1_学習WBS'!$B$3:$B$96,$A9,'1_学習WBS'!$H$3:$H$96,"○") | D9: =COUNTIFS('1_学習WBS'!$B$3:$B$96,$A9,'1_学習WBS'!$H$3:$H$96,"△") | E9: =COUNTIFS('1_学習WBS'!$B$3:$B$96,$A9,'1_学習WBS'!$H$3:$H$96,"×") | F9: =IF(B9=0,"",ROUND(C9/B9*100,0)&" %")
A10: F 練習③ | B10: =COUNTIF('1_学習WBS'!$B$3:$B$96,$A10) | C10: =COUNTIFS('1_学習WBS'!$B$3:$B$96,$A10,'1_学習WBS'!$H$3:$H$96,"○") | D10: =COUNTIFS('1_学習WBS'!$B$3:$B$96,$A10,'1_学習WBS'!$H$3:$H$96,"△") | E10: =COUNTIFS('1_学習WBS'!$B$3:$B$96,$A10,'1_学習WBS'!$H$3:$H$96,"×") | F10: =IF(B10=0,"",ROUND(C10/B10*100,0)&" %")
A11: F 練習③（验收） | B11: =COUNTIF('1_学習WBS'!$B$3:$B$96,$A11) | C11: =COUNTIFS('1_学習WBS'!$B$3:$B$96,$A11,'1_学習WBS'!$H$3:$H$96,"○") | D11: =COUNTIFS('1_学習WBS'!$B$3:$B$96,$A11,'1_学習WBS'!$H$3:$H$96,"△") | E11: =COUNTIFS('1_学習WBS'!$B$3:$B$96,$A11,'1_学習WBS'!$H$3:$H$96,"×") | F11: =IF(B11=0,"",ROUND(C11/B11*100,0)&" %")
A12: G 練習④ | B12: =COUNTIF('1_学習WBS'!$B$3:$B$96,$A12) | C12: =COUNTIFS('1_学習WBS'!$B$3:$B$96,$A12,'1_学習WBS'!$H$3:$H$96,"○") | D12: =COUNTIFS('1_学習WBS'!$B$3:$B$96,$A12,'1_学習WBS'!$H$3:$H$96,"△") | E12: =COUNTIFS('1_学習WBS'!$B$3:$B$96,$A12,'1_学習WBS'!$H$3:$H$96,"×") | F12: =IF(B12=0,"",ROUND(C12/B12*100,0)&" %")
A13: G 練習④（验收） | B13: =COUNTIF('1_学習WBS'!$B$3:$B$96,$A13) | C13: =COUNTIFS('1_学習WBS'!$B$3:$B$96,$A13,'1_学習WBS'!$H$3:$H$96,"○") | D13: =COUNTIFS('1_学習WBS'!$B$3:$B$96,$A13,'1_学習WBS'!$H$3:$H$96,"△") | E13: =COUNTIFS('1_学習WBS'!$B$3:$B$96,$A13,'1_学習WBS'!$H$3:$H$96,"×") | F13: =IF(B13=0,"",ROUND(C13/B13*100,0)&" %")
A14: H 練習⑤（発展・故障） | B14: =COUNTIF('1_学習WBS'!$B$3:$B$96,$A14) | C14: =COUNTIFS('1_学習WBS'!$B$3:$B$96,$A14,'1_学習WBS'!$H$3:$H$96,"○") | D14: =COUNTIFS('1_学習WBS'!$B$3:$B$96,$A14,'1_学習WBS'!$H$3:$H$96,"△") | E14: =COUNTIFS('1_学習WBS'!$B$3:$B$96,$A14,'1_学習WBS'!$H$3:$H$96,"×") | F14: =IF(B14=0,"",ROUND(C14/B14*100,0)&" %")
... A17: J テスト | B17: =COUNTIF('1_学習WBS'!$B$3:$B$96,$A17) | C17: =COUNTIFS('1_学習WBS'!$B$3:$B$96,$A17,'1_学習WBS'!$H$3:$H$96,"○") | D17: =COUNTIFS('1_学習WBS'!$B$3:$B$96,$A17,'1_学習WBS'!$H$3:$H$96,"△") | E17: =COUNTIFS('1_学習WBS'!$B$3:$B$96,$A17,'1_学習WBS'!$H$3:$H$96,"×") | F17: =IF(B17=0,"",ROUND(C17/B17*100,0)&" %")
A18: 合計 / 全体 | B18: =SUM(B3:B17) | C18: =SUM(C3:C17) | D18: =SUM(D3:D17) | E18: =SUM(E3:E17) | F18: =IF(B18=0,"",ROUND(C18/B18*100,0)&" %")
A20: 実施合計時間（分） | B20: =SUM('1_学習WBS'!$F$3:$F$96)
A21: ○ のみの合計時間（分） | B21: =SUMIFS('1_学習WBS'!$F$3:$F$96,'1_学習WBS'!$H$3:$H$96,"○")

Sheet 3_実機記録
A1: 実機記録（伝票番号・数値・証跡）— 講師の確認対象
A2: # | B2: 記録項目 | C2: 期待値・見方 | D2: 実測値 / 伝票番号 | E2: 実施日 | F2: 証跡メモ
A3: 1 | B3: PIR 登録（MD61）の品目・数量・期間 | C3: 月次 500 PC など
A4: 2 | B4: MD04 の需要行（PIR / 受注） | C4: 消費後の残を記録
A5: 3 | B5: 計画手配番号（MD04） | C5: MRP 実行後に生成
A6: 4 | B6: 製造指図番号（CO01 / CO40） | C6: 標準原価が入っていること
A7: 5 | B7: 部品出庫（261）・完成品入庫（101）の数量 | C7: 指図数量と一致
A8: 6 | B8: 自由在庫の数量（MMBE / MB52） | C8: 入庫後に増加
A9: 7 | B9: 受注番号と引当結果（CO09） | C9: 不足なし／不足数量
A10: 8 | B10: 出荷・請求の伝票番号（VL01N / VF01） | C10: 数量・金額
A11: 9 | B11: 指図の差異額（KKS1 / KO88） | C11: 標準原価との差（±）
A12: 10 | B12: 伝票フロー（VA03）に揃った伝票 | C12: 受注 → 引当 → 出荷 → 請求

Sheet 4_修了判定
A1: 修了判定（到達点チェックと講師確認）
A2: # | B2: 到達点（これが言えたら本教材は修了） | C2: チェック
A3: 1 | B3: PIR → MRP → 指図 → 入庫 → 受注 → 出荷 → 請求 を 1 人で通した
A4: 2 | B4: 自由在庫（MARD）と受注在庫（MSKA）の違いを、実機の画面で説明できた
A5: 3 | B5: 受注が PIR を消費する挙動を MD04 で確認した
A6: 4 | B6: 差異計算と決済（KKS1 / KO88 / CO88）を 1 回実行した
A7: 5 | B7: MTO 站（sapmto）との違いを 5 点で説明できた
A8: 6 | B8: 能力测试（quiz.html）で 75% 以上
A10: 再受講が必要な分野（△ × のあったフェーズ）
A11: 講師所見
A12: 実施日 / 講師署名
